toolsmith/__init__.py
toolsmith/toolbox.py
toolsmith/toolsmith.py
toolsmith-0.2.0.dist-info/LICENSE
toolsmith-0.2.0.dist-info/METADATA
toolsmith-0.2.0.dist-info/WHEEL
toolsmith-0.2.0.dist-info/RECORD
