Metadata-Version: 2.3
Name: toolsmith
Version: 0.2.0
Summary: Instantly turn your Python functions into structured, AI-callable tools.
License: MIT
Author: Douglas Li
Author-email: lidouglas@gmail.com
Requires-Python: >=3.9,<4.0
Classifier: License :: OSI Approved :: MIT License
Classifier: Programming Language :: Python :: 3
Classifier: Programming Language :: Python :: 3.9
Classifier: Programming Language :: Python :: 3.10
Classifier: Programming Language :: Python :: 3.11
Classifier: Programming Language :: Python :: 3.12
Classifier: Programming Language :: Python :: 3.13
Requires-Dist: openai (>=1.67.0,<2.0.0)
Requires-Dist: pydantic (>=2.10.6,<3.0.0)
Project-URL: Repository, https://github.com/dougli/toolsmith
